dodgem/__init__.py
dodgem/dodgem.py
dodgem-1.3.2.dist-info/LICENSE
dodgem-1.3.2.dist-info/METADATA
dodgem-1.3.2.dist-info/WHEEL
dodgem-1.3.2.dist-info/entry_points.txt
dodgem-1.3.2.dist-info/RECORD
