Metadata-Version: 2.3
Name: dodgem
Version: 1.3.2
Summary: Version bumper for Python.
Author: Saul Johnson
Author-email: saul.a.johnson@gmail.com
Requires-Python: >=3.6,<4.0
Classifier: Programming Language :: Python :: 3
Classifier: Programming Language :: Python :: 3.6
Classifier: Programming Language :: Python :: 3.7
Classifier: Programming Language :: Python :: 3.8
Classifier: Programming Language :: Python :: 3.9
Classifier: Programming Language :: Python :: 3.10
Classifier: Programming Language :: Python :: 3.11
Classifier: Programming Language :: Python :: 3.12
Classifier: Programming Language :: Python :: 3.13
Requires-Dist: blessings (>=1.7,<2.0)
Requires-Dist: click (>=8.0.4,<9.0.0)
Requires-Dist: semver (>=2.13.0,<3.0.0)
Requires-Dist: tomlkit (>=0.10.2,<0.11.0)
Project-URL: Repository, https://github.com/lambdacasserole/dodgem.git
